monorepo/__init__.py
monorepo-0.2.0.dist-info/LICENSE
monorepo-0.2.0.dist-info/METADATA
monorepo-0.2.0.dist-info/WHEEL
monorepo-0.2.0.dist-info/top_level.txt
monorepo-0.2.0.dist-info/RECORD
