Metadata-Version: 2.1
Name: monorepo
Version: 0.2.0
Summary: Import packages and modules from the root of a monorepo
Home-page: https://github.com/myleott/monorepo
Requires-Python: >=3.8
License-File: LICENSE
